project/m2/rtl/compute_core.sv
/*
 * Module: compute_core
 * Description: Synthesizable compute core for HW4AI Milestone 2.
 * Implements a pipelined Multiply-Accumulate (MAC) datapath.
 *
 * Clock Domain:
 * - clk: Single clock domain for all clocked logic. No domain crossings.
 *
 * Reset Behavior:
 * - rst: Synchronous, active-high reset. Clears the accumulator and valid flag.
 *
 * Ports:
 * - clk       : input  : 1-bit  : System clock
 * - rst       : input  : 1-bit  : Synchronous active-high reset
 * - valid_in  : input  : 1-bit  : Control signal indicating inputs are valid
 * - a_in      : input  : 8-bit  : Signed 8-bit data input A
 * - b_in      : input  : 8-bit  : Signed 8-bit data input B (or weight)
 * - valid_out : output : 1-bit  : Control signal indicating output data is valid
 * - result    : output : 32-bit : Signed 32-bit accumulated output
 */

module compute_core (
    input  logic               clk,
    input  logic               rst,
    input  logic               valid_in,
    input  logic signed  [7:0] a_in,
    input  logic signed  [7:0] b_in,
    output logic               valid_out,
    output logic signed [31:0] result
);

    // Internal registers
    logic signed [31:0] accumulator;
    logic               out_flag;

    always_ff @(posedge clk) begin
        if (rst) begin
            accumulator <= 32'sd0;
            out_flag    <= 1'b0;
        end else if (valid_in) begin
            // Explicit 32-bit cast to prevent width mismatch warnings
            accumulator <= accumulator + 32'(a_in * b_in);
            out_flag    <= 1'b1;
        end else begin
            out_flag    <= 1'b0;
        end
    end

    // Continuous assignment to outputs
    assign result = accumulator;
    assign valid_out = out_flag;

endmodule

project/m2/tb/tb_compute_core.sv
`timescale 1ns/1ps

/*
 * Module: tb_compute_core
 * Description: Testbench for the MAC compute core.
 * Verifies accumulation over several cycles and asserts PASS/FAIL.
 */

module tb_compute_core;

    // Signals
    logic               clk;
    logic               rst;
    logic               valid_in;
    logic signed  [7:0] a_in;
    logic signed  [7:0] b_in;
    logic               valid_out;
    logic signed [31:0] result;

    // Expected reference variable
    logic signed [31:0] expected_acc;
    int                 error_count;

    // Instantiate the Device Under Test (DUT)
    compute_core dut (
        .clk(clk),
        .rst(rst),
        .valid_in(valid_in),
        .a_in(a_in),
        .b_in(b_in),
        .valid_out(valid_out),
        .result(result)
    );

    // Clock generation (10ns period)
    initial begin
        clk = 0;
        forever #5 clk = ~clk;
    end

    // Test sequence
    initial begin
        // Initialize VCD dumping for waveform visualization
        $dumpfile("project/m2/sim/compute_core.vcd");
        $dumpvars(0, tb_compute_core);

        // Initialize inputs
        rst = 1;
        valid_in = 0;
        a_in = 0;
        b_in = 0;
        expected_acc = 0;
        error_count = 0;

        // Hold reset for a couple of cycles
        @(negedge clk);
        @(negedge clk);
        rst = 0;

        // --- Test Vector 1 ---
        @(negedge clk);
        valid_in = 1;
        a_in = 8'd5;
        b_in = 8'd2;
        expected_acc = expected_acc + (5 * 2); // 10

        // --- Test Vector 2 (Negative Numbers) ---
        @(negedge clk);
        a_in = -8'sd3;
        b_in = 8'd4;
        expected_acc = expected_acc + (-3 * 4); // 10 - 12 = -2

        // --- Test Vector 3 ---
        @(negedge clk);
        a_in = 8'd10;
        b_in = 8'd10;
        expected_acc = expected_acc + (10 * 10); // -2 + 100 = 98

        // Stop driving inputs
        @(negedge clk);
        valid_in = 0;
        a_in = 0;
        b_in = 0;

        // Wait one cycle for the final valid_out to register
        @(posedge clk);
        #1; // Slight delay to ensure signals have updated

        // Check the final result
        if (result !== expected_acc) begin
            $display("ERROR: Final accumulation mismatch. Expected %0d, Got %0d", expected_acc, result);
            error_count++;
        end

        // Print final grading status
        $display("---------------------------------");
        if (error_count == 0) begin
            $display("SIMULATION RESULT: PASS");
        end else begin
            $display("SIMULATION RESULT: FAIL (%0d errors)", error_count);
        end
        $display("---------------------------------");

        $finish;
    end

endmodule

project/m2/sim/compute_core.vcd
$date
	Sat May  2 18:18:19 2026
$end
$version
	Icarus Verilog
$end
$timescale
	1ps
$end
$scope module tb_compute_core $end
$var wire 1 ! valid_out $end
$var wire 32 " result [31:0] $end
$var reg 8 # a_in [7:0] $end
$var reg 8 $ b_in [7:0] $end
$var reg 1 % clk $end
$var reg 32 & expected_acc [31:0] $end
$var reg 1 ' rst $end
$var reg 1 ( valid_in $end
$var integer 32 ) error_count [31:0] $end
$scope module dut $end
$var wire 8 * a_in [7:0] $end
$var wire 8 + b_in [7:0] $end
$var wire 1 % clk $end
$var wire 32 , result [31:0] $end
$var wire 1 ' rst $end
$var wire 1 ( valid_in $end
$var wire 1 ! valid_out $end
$var reg 32 - accumulator [31:0] $end
$var reg 1 . out_flag $end
$upscope $end
$upscope $end
$enddefinitions $end
$comment Show the parameter values. $end
$dumpall
$end
#0
$dumpvars
x.
bx -
bx ,
b0 +
b0 *
b0 )
0(
1'
b0 &
0%
b0 $
b0 #
bx "
x!
$end
#5000
0!
0.
b0 "
b0 ,
b0 -
1%
#10000
0%
#15000
1%
#20000
0'
0%
#25000
1%
#30000
b1010 &
b10 $
b10 +
b101 #
b101 *
1(
0%
#35000
1!
1.
b1010 "
b1010 ,
b1010 -
1%
#40000
b11111111111111111111111111111110 &
b100 $
b100 +
b11111101 #
b11111101 *
0%
#45000
b11111111111111111111111111111110 "
b11111111111111111111111111111110 ,
b11111111111111111111111111111110 -
1%
#50000
b1100010 &
b1010 $
b1010 +
b1010 #
b1010 *
0%
#55000
b1100010 "
b1100010 ,
b1100010 -
1%
#60000
b0 $
b0 +
b0 #
b0 *
0(
0%
#65000
0!
0.
1%
