project/m2/rtl/compute_core.sv
/*
 * Module: compute_core
 * Description: Synthesizable compute core for HW4AI Milestone 2.
 * Implements a pipelined Multiply-Accumulate (MAC) datapath.
 *
 * Clock Domain:
 * - clk: Single clock domain for all clocked logic. No domain crossings.
 *
 * Reset Behavior:
 * - rst: Synchronous, active-high reset. Clears the accumulator and valid flag.
 *
 * Ports:
 * - clk       : input  : 1-bit  : System clock
 * - rst       : input  : 1-bit  : Synchronous active-high reset
 * - valid_in  : input  : 1-bit  : Control signal indicating inputs are valid
 * - a_in      : input  : 8-bit  : Signed 8-bit data input A
 * - b_in      : input  : 8-bit  : Signed 8-bit data input B (or weight)
 * - valid_out : output : 1-bit  : Control signal indicating output data is valid
 * - result    : output : 32-bit : Signed 32-bit accumulated output
 */

module compute_core (
    input  logic               clk,
    input  logic               rst,
    input  logic               valid_in,
    input  logic signed  [7:0] a_in,
    input  logic signed  [7:0] b_in,
    output logic               valid_out,
    output logic signed [31:0] result
);

    // Internal registers
    logic signed [31:0] accumulator;
    logic               out_flag;

    always_ff @(posedge clk) begin
        if (rst) begin
            accumulator <= 32'sd0;
            out_flag    <= 1'b0;
        end else if (valid_in) begin
            // Explicit 32-bit cast to prevent width mismatch warnings
            accumulator <= accumulator + 32'(a_in * b_in);
            out_flag    <= 1'b1;
        end else begin
            out_flag    <= 1'b0;
        end
    end

    // Continuous assignment to outputs
    assign result = accumulator;
    assign valid_out = out_flag;

endmodule

project/MTest/rtl/interface.sv
/*
 * Module: axi_interface
 * Description: Synthesizable AXI4-Stream interface for HW4AI Milestone 2.
 * Receives packed 8-bit inputs (A and B) and transmits 32-bit results.
 *
 * Protocol: AXI4-Stream
 * - Honors TVALID/TREADY contract on both Subordinate (receive) and Manager (transmit) interfaces.
 *
 * Transaction Format:
 * - s_axis_tdata [15:0] : Lower 8 bits = a_in, Upper 8 bits = b_in
 * - m_axis_tdata [31:0] : 32-bit accumulated result
 *
 * Clock Domain:
 * - clk: Single clock domain for all clocked logic.
 *
 * Reset Behavior:
 * - rst: Synchronous, active-high reset. Clears all valid signals and state.
 *
 * Ports:
 * - clk            : input  : 1-bit  : System clock
 * - rst            : input  : 1-bit  : Synchronous active-high reset
 * * -- AXI4-Stream Subordinate Interface (Receiving Data) --
 * - s_axis_tvalid  : input  : 1-bit  : Manager indicates data is valid
 * - s_axis_tready  : output : 1-bit  : Subordinate is ready to accept data
 * - s_axis_tdata   : input  : 16-bit : Packed input data {b_in[7:0], a_in[7:0]}
 *
 * -- AXI4-Stream Manager Interface (Transmitting Data) --
 * - m_axis_tvalid  : output : 1-bit  : Manager indicates result is valid
 * - m_axis_tready  : input  : 1-bit  : Subordinate is ready to accept result
 * - m_axis_tdata   : output : 32-bit : Output result data
 *
 * -- Internal Compute Core Interface --
 * - core_valid_in  : output : 1-bit  : Drive compute core valid
 * - core_a_in      : output : 8-bit  : Unpacked A input
 * - core_b_in      : output : 8-bit  : Unpacked B input
 * - core_valid_out : input  : 1-bit  : Compute core valid flag
 * - core_result    : input  : 32-bit : Compute core result
 */

module axi_interface (
    input  logic               clk,
    input  logic               rst,

    // AXI4-Stream Subordinate (Inbound)
    input  logic               s_axis_tvalid,
    output logic               s_axis_tready,
    input  logic [15:0]        s_axis_tdata,

    // AXI4-Stream Manager (Outbound)
    output logic               m_axis_tvalid,
    input  logic               m_axis_tready,
    output logic [31:0]        m_axis_tdata,

    // Signals mapped to compute_core.sv
    output logic               core_valid_in,
    output logic signed [7:0]  core_a_in,
    output logic signed [7:0]  core_b_in,
    input  logic               core_valid_out,
    input  logic signed [31:0] core_result
);

    // The interface is ready to accept new data when the downstream sink is ready,
    // or if no valid output is currently pending.
    assign s_axis_tready = m_axis_tready || !m_axis_tvalid;

    // Unpack AXI-Stream data into the compute core format
    assign core_a_in     = s_axis_tdata[7:0];
    assign core_b_in     = s_axis_tdata[15:8];
    
    // Only trigger the core if we have valid input AND we are ready to accept it
    assign core_valid_in = s_axis_tvalid && s_axis_tready;

    // Buffer to hold output valid state to satisfy AXI-Stream handshake
    always_ff @(posedge clk) begin
        if (rst) begin
            m_axis_tvalid <= 1'b0;
            m_axis_tdata  <= 32'd0;
        end else begin
            // Capture core output when valid
            if (core_valid_out) begin
                m_axis_tvalid <= 1'b1;
                m_axis_tdata  <= core_result;
            end 
            // Clear valid flag once the downstream subordinate accepts the data
            else if (m_axis_tready && m_axis_tvalid) begin
                m_axis_tvalid <= 1'b0;
            end
        end
    end

endmodule

project/m2/tb/tb_interface.sv
`timescale 1ns/1ps

/*
 * Module: tb_interface
 * Description: Testbench for the AXI4-Stream interface.
 * Verifies TVALID/TREADY handshaking and data unpacking/packing
 * by wrapping the compute_core.
 */

module tb_interface;

    // Clock and Reset
    logic clk;
    logic rst;

    // AXI4-Stream Subordinate (Inbound to DUT)
    logic        s_axis_tvalid;
    logic        s_axis_tready;
    logic [15:0] s_axis_tdata;

    // AXI4-Stream Manager (Outbound from DUT)
    logic        m_axis_tvalid;
    logic        m_axis_tready;
    logic [31:0] m_axis_tdata;

    // Internal connections between Interface and Compute Core
    logic               core_valid_in;
    logic signed  [7:0] core_a_in;
    logic signed  [7:0] core_b_in;
    logic               core_valid_out;
    logic signed [31:0] core_result;

    int error_count;

    // Instantiate the Interface (DUT) with the corrected module name
    axi_interface dut_if (
        .clk(clk),
        .rst(rst),
        .s_axis_tvalid(s_axis_tvalid),
        .s_axis_tready(s_axis_tready),
        .s_axis_tdata(s_axis_tdata),
        .m_axis_tvalid(m_axis_tvalid),
        .m_axis_tready(m_axis_tready),
        .m_axis_tdata(m_axis_tdata),
        .core_valid_in(core_valid_in),
        .core_a_in(core_a_in),
        .core_b_in(core_b_in),
        .core_valid_out(core_valid_out),
        .core_result(core_result)
    );

    // Instantiate the Compute Core
    compute_core dut_core (
        .clk(clk),
        .rst(rst),
        .valid_in(core_valid_in),
        .a_in(core_a_in),
        .b_in(core_b_in),
        .valid_out(core_valid_out),
        .result(core_result)
    );

    // Clock generation (10ns period)
    initial begin
        clk = 0;
        forever #5 clk = ~clk;
    end

    // Test sequence
    initial begin
        // Initialize VCD dumping
        $dumpfile("project/m2/sim/interface.vcd");
        $dumpvars(0, tb_interface);

        // Initialize signals
        rst = 1;
        s_axis_tvalid = 0;
        s_axis_tdata = 0;
        m_axis_tready = 0;
        error_count = 0;

        // Release reset
        @(negedge clk);
        @(negedge clk);
        rst = 0;

        // ---------------------------------------------------------
        // Test 1: Standard AXI-Stream Write & Read
        // Send a = 5, b = 3. Expected Result = 15.
        // ---------------------------------------------------------
        @(negedge clk);
        s_axis_tvalid = 1;
        s_axis_tdata  = {8'd3, 8'd5}; // {b_in, a_in}
        m_axis_tready = 1;            // Downstream is ready

        // Wait for interface to accept data
        wait(s_axis_tready == 1'b1);
        @(negedge clk);
        s_axis_tvalid = 0; // De-assert after acceptance

        // Wait for result to pop out
        wait(m_axis_tvalid == 1'b1);
        
        if (m_axis_tdata !== 32'd15) begin
            $display("ERROR (Test 1): Expected 15, Got %0d", m_axis_tdata);
            error_count++;
        end

        // *** THE CRITICAL FIX ***
        // Wait for the next clock edges so the interface registers 
        // that the handshake is complete and clears out the 15!
        @(posedge clk);
        @(negedge clk);

        // ---------------------------------------------------------
        // Test 2: Backpressure (m_axis_tready is LOW)
        // Send a = -2, b = 4. Expected Accumulation = 15 + (-8) = 7
        // ---------------------------------------------------------
        s_axis_tvalid = 1;
        s_axis_tdata  = {8'd4, -8'sd2}; 
        m_axis_tready = 0; // Downstream is NOT ready yet

        wait(s_axis_tready == 1'b1);
        @(negedge clk);
        s_axis_tvalid = 0;

        // Wait for the new valid flag to pop up
        wait(m_axis_tvalid == 1'b1);
        
        // Wait two cycles to prove it holds the data while backpressured
        @(posedge clk);
        @(posedge clk);
        
        if (m_axis_tvalid !== 1'b1) begin
            $display("ERROR (Test 2): Interface dropped valid flag during backpressure.");
            error_count++;
        end

        // Now assert ready to consume the data
        @(negedge clk);
        m_axis_tready = 1;

        @(posedge clk);
        #1;
        if (m_axis_tdata !== 32'd7) begin
            $display("ERROR (Test 2): Expected 7, Got %0d", m_axis_tdata);
            error_count++;
        end

        // ---------------------------------------------------------
        // End of Simulation
        // ---------------------------------------------------------
        @(negedge clk);
        $display("---------------------------------");
        if (error_count == 0) begin
            $display("SIMULATION RESULT: PASS");
        end else begin
            $display("SIMULATION RESULT: FAIL (%0d errors)", error_count);
        end
        $display("---------------------------------");

        $finish;
    end

endmodule

project/m2/sim/interface.vcd
$date
	Sat May  2 18:11:35 2026
$end
$version
	Icarus Verilog
$end
$timescale
	1ps
$end
$scope module tb_interface $end
$var wire 1 ! s_axis_tready $end
$var wire 1 " m_axis_tvalid $end
$var wire 32 # m_axis_tdata [31:0] $end
$var wire 1 $ core_valid_out $end
$var wire 1 % core_valid_in $end
$var wire 32 & core_result [31:0] $end
$var wire 8 ' core_b_in [7:0] $end
$var wire 8 ( core_a_in [7:0] $end
$var reg 1 ) clk $end
$var reg 1 * m_axis_tready $end
$var reg 1 + rst $end
$var reg 16 , s_axis_tdata [15:0] $end
$var reg 1 - s_axis_tvalid $end
$var integer 32 . error_count [31:0] $end
$scope module dut_core $end
$var wire 1 ) clk $end
$var wire 32 / result [31:0] $end
$var wire 1 + rst $end
$var wire 1 $ valid_out $end
$var wire 1 % valid_in $end
$var wire 8 0 b_in [7:0] $end
$var wire 8 1 a_in [7:0] $end
$var reg 32 2 accumulator [31:0] $end
$var reg 1 3 out_flag $end
$upscope $end
$scope module dut_if $end
$var wire 1 ) clk $end
$var wire 32 4 core_result [31:0] $end
$var wire 1 % core_valid_in $end
$var wire 1 $ core_valid_out $end
$var wire 1 * m_axis_tready $end
$var wire 1 + rst $end
$var wire 16 5 s_axis_tdata [15:0] $end
$var wire 1 ! s_axis_tready $end
$var wire 1 - s_axis_tvalid $end
$var wire 8 6 core_b_in [7:0] $end
$var wire 8 7 core_a_in [7:0] $end
$var reg 32 8 m_axis_tdata [31:0] $end
$var reg 1 " m_axis_tvalid $end
$upscope $end
$upscope $end
$enddefinitions $end
$comment Show the parameter values. $end
$dumpall
$end
#0
$dumpvars
bx 8
b0 7
b0 6
b0 5
bx 4
x3
bx 2
b0 1
b0 0
bx /
b0 .
0-
b0 ,
1+
0*
0)
b0 (
b0 '
bx &
0%
x$
bx #
x"
x!
$end
#5000
1!
b0 #
b0 8
0"
0$
03
b0 &
b0 /
b0 4
b0 2
1)
#10000
0)
#15000
1)
#20000
0+
0)
#25000
1)
#30000
b101 (
b101 1
b101 7
b11 '
b11 0
b11 6
1%
1*
b1100000101 ,
b1100000101 5
1-
0)
#35000
1$
13
b1111 &
b1111 /
b1111 4
b1111 2
1)
#40000
0%
0-
0)
#45000
b1111 #
b1111 8
1"
0$
03
1)
#50000
0)
#55000
0"
1)
#60000
b11111110 (
b11111110 1
b11111110 7
b100 '
b100 0
b100 6
1%
0*
b10011111110 ,
b10011111110 5
1-
0)
#65000
1$
13
b111 &
b111 /
b111 4
b111 2
1)
#70000
0%
0-
0)
#75000
0!
0$
03
b111 #
b111 8
1"
1)
#80000
0)
#85000
1)
#90000
0)
#95000
1)
#100000
1!
1*
0)
#105000
0"
1)
