project/m4/rtl/compute_core.sv
module compute_core (
    input  logic        clk,
    input  logic        rst,       
    input  logic        valid_in,  
    input  logic [7:0]  a_in,      
    input  logic [7:0]  b_in,      
    output logic        valid_out, 
    output logic [31:0] result     
);

    // --- 1. Architectural Parameters ---
    localparam int IMG_WIDTH = 28;
    
    // Flattened 3x3 kernel weights for iverilog compatibility
    localparam signed [7:0] W00 =  8'sd1; localparam signed [7:0] W01 =  8'sd2; localparam signed [7:0] W02 =  8'sd1;
    localparam signed [7:0] W10 =  8'sd0; localparam signed [7:0] W11 =  8'sd0; localparam signed [7:0] W12 =  8'sd0;
    localparam signed [7:0] W20 = -8'sd1; localparam signed [7:0] W21 = -8'sd2; localparam signed [7:0] W22 = -8'sd1;

    // --- 2. The Sliding Window & Line Buffers ---
    // To achieve exactly 28 cycles of delay per row:
    // 3 cycles in the window + 25 cycles in the buffer = 28 cycles.
    // 25 elements = indices 0 to 24 (IMG_WIDTH - 4).
    logic signed [7:0] window [0:2][0:2];
    logic signed [7:0] line_buf_1 [0:IMG_WIDTH-4];
    logic signed [7:0] line_buf_2 [0:IMG_WIDTH-4];

    // --- 3. Control Counters ---
    logic [4:0] col_cnt; // Counts 0 to 27
    logic [4:0] row_cnt; // Counts 0 to 27
    logic       window_valid;

    // --- 4. The Dataflow Shift Logic ---
    always_ff @(posedge clk) begin
        if (rst) begin
            col_cnt <= '0;
            row_cnt <= '0;
        end 
        else if (valid_in) begin
            // Shift the 3x3 Window
            window[0][0] <= window[0][1]; window[0][1] <= window[0][2];
            window[1][0] <= window[1][1]; window[1][1] <= window[1][2];
            window[2][0] <= window[2][1]; window[2][1] <= window[2][2];

            // Feed the right-most column of the window
            window[0][2] <= line_buf_2[IMG_WIDTH-4]; 
            window[1][2] <= line_buf_1[IMG_WIDTH-4]; 
            window[2][2] <= a_in;            

            // Shift the Line Buffers
            for (int i = IMG_WIDTH-4; i > 0; i--) begin
                line_buf_1[i] <= line_buf_1[i-1];
                line_buf_2[i] <= line_buf_2[i-1];
            end
            
            // Push the pixels falling out of the window into the buffers
            line_buf_1[0] <= window[2][0]; 
            line_buf_2[0] <= window[1][0];

            // Update Image Position Counters
            if (col_cnt == IMG_WIDTH - 1) begin
                col_cnt <= '0;
                if (row_cnt != IMG_WIDTH - 1)
                    row_cnt <= row_cnt + 1;
            end else begin
                col_cnt <= col_cnt + 1;
            end
        end
    end

    // --- 5. Validity Control (The Edge Case Logic) ---
    assign window_valid = (row_cnt >= 2) && (col_cnt >= 2);

    // --- 6. Pipeline Synchronization ---
    logic valid_pipe_1, valid_pipe_2;

    always_ff @(posedge clk) begin
        if (rst) begin
            valid_pipe_1 <= 1'b0;
            valid_pipe_2 <= 1'b0;
        end else begin 
            valid_pipe_1 <= window_valid && valid_in;
            valid_pipe_2 <= valid_pipe_1;
        end
    end

    assign valid_out = valid_pipe_2;

    // --- 7. PIPELINE STAGE 1: Multiplication ---
    logic signed [15:0] prod [0:8]; 

    always_ff @(posedge clk) begin
        if (rst) begin
            for (int i=0; i<9; i++) prod[i] <= '0;
        end else if (valid_in && window_valid) begin
            prod[0] <= window[0][0] * W00;
            prod[1] <= window[0][1] * W01;
            prod[2] <= window[0][2] * W02;
            
            prod[3] <= window[1][0] * W10;
            prod[4] <= window[1][1] * W11;
            prod[5] <= window[1][2] * W12;
            
            prod[6] <= window[2][0] * W20;
            prod[7] <= window[2][1] * W21;
            prod[8] <= window[2][2] * W22;
        end
    end

    // --- 8. PIPELINE STAGE 2: Accumulation ---
    logic signed [31:0] sum;

    always_ff @(posedge clk) begin
        if (rst) begin
            sum <= '0;
        end else if (valid_pipe_1) begin
            sum <= prod[0] + prod[1] + prod[2] + 
                   prod[3] + prod[4] + prod[5] + 
                   prod[6] + prod[7] + prod[8];
        end
    end

    assign result = sum;

endmodule

project/MTest/rtl/interface.sv
/*
 * Module: axi_interface
 * Description: Synthesizable AXI4-Stream interface for HW4AI Milestone 2.
 * Receives packed 8-bit inputs (A and B) and transmits 32-bit results.
 *
 * Protocol: AXI4-Stream
 * - Honors TVALID/TREADY contract on both Subordinate (receive) and Manager (transmit) interfaces.
 *
 * Transaction Format:
 * - s_axis_tdata [15:0] : Lower 8 bits = a_in, Upper 8 bits = b_in
 * - m_axis_tdata [31:0] : 32-bit accumulated result
 *
 * Clock Domain:
 * - clk: Single clock domain for all clocked logic.
 *
 * Reset Behavior:
 * - rst: Synchronous, active-high reset. Clears all valid signals and state.
 *
 * Ports:
 * - clk            : input  : 1-bit  : System clock
 * - rst            : input  : 1-bit  : Synchronous active-high reset
 * * -- AXI4-Stream Subordinate Interface (Receiving Data) --
 * - s_axis_tvalid  : input  : 1-bit  : Manager indicates data is valid
 * - s_axis_tready  : output : 1-bit  : Subordinate is ready to accept data
 * - s_axis_tdata   : input  : 16-bit : Packed input data {b_in[7:0], a_in[7:0]}
 *
 * -- AXI4-Stream Manager Interface (Transmitting Data) --
 * - m_axis_tvalid  : output : 1-bit  : Manager indicates result is valid
 * - m_axis_tready  : input  : 1-bit  : Subordinate is ready to accept result
 * - m_axis_tdata   : output : 32-bit : Output result data
 *
 * -- Internal Compute Core Interface --
 * - core_valid_in  : output : 1-bit  : Drive compute core valid
 * - core_a_in      : output : 8-bit  : Unpacked A input
 * - core_b_in      : output : 8-bit  : Unpacked B input
 * - core_valid_out : input  : 1-bit  : Compute core valid flag
 * - core_result    : input  : 32-bit : Compute core result
 */

module axi_interface (
    input  logic               clk,
    input  logic               rst,

    // AXI4-Stream Subordinate (Inbound)
    input  logic               s_axis_tvalid,
    output logic               s_axis_tready,
    input  logic [15:0]        s_axis_tdata,

    // AXI4-Stream Manager (Outbound)
    output logic               m_axis_tvalid,
    input  logic               m_axis_tready,
    output logic [31:0]        m_axis_tdata,

    // Signals mapped to compute_core.sv
    output logic               core_valid_in,
    output logic signed [7:0]  core_a_in,
    output logic signed [7:0]  core_b_in,
    input  logic               core_valid_out,
    input  logic signed [31:0] core_result
);

    // The interface is ready to accept new data when the downstream sink is ready,
    // or if no valid output is currently pending.
    assign s_axis_tready = m_axis_tready || !m_axis_tvalid;

    // Unpack AXI-Stream data into the compute core format
    assign core_a_in     = s_axis_tdata[7:0];
    assign core_b_in     = s_axis_tdata[15:8];
    
    // Only trigger the core if we have valid input AND we are ready to accept it
    assign core_valid_in = s_axis_tvalid && s_axis_tready;

    // Buffer to hold output valid state to satisfy AXI-Stream handshake
    always_ff @(posedge clk) begin
        if (rst) begin
            m_axis_tvalid <= 1'b0;
            m_axis_tdata  <= 32'd0;
        end else begin
            // Capture core output when valid
            if (core_valid_out) begin
                m_axis_tvalid <= 1'b1;
                m_axis_tdata  <= core_result;
            end 
            // Clear valid flag once the downstream subordinate accepts the data
            else if (m_axis_tready && m_axis_tvalid) begin
                m_axis_tvalid <= 1'b0;
            end
        end
    end

endmodule

project/MTest/rtl/top.sv
`timescale 1ns / 1ps

// `include "interface.sv"
// `include "compute_core.sv"

/* =========================================================================
 * Module: top
 * Description: Integrated top-level module connecting the AXI4-Stream interface
 * to the 2D convolution compute core.
 *
 * External Port List:
 * clk           - Input  - 1-bit  - Main system clock
 * rst           - Input  - 1-bit  - Active-high synchronous reset
 * s_axis_tvalid - Input  - 1-bit  - Subordinate AXI stream valid signal (host to core)
 * s_axis_tready - Output - 1-bit  - Subordinate AXI stream ready signal (core to host)
 * s_axis_tdata  - Input  - 16-bit - Subordinate AXI stream data (packed A and B operands)
 * m_axis_tvalid - Output - 1-bit  - Manager AXI stream valid signal (core to host)
 * m_axis_tready - Input  - 1-bit  - Manager AXI stream ready signal (host to core)
 * m_axis_tdata  - Output - 32-bit - Manager AXI stream data (convolution result)
 * ========================================================================= */

module top (
    input  logic               clk,
    input  logic               rst,

    // AXI4-Stream Subordinate (Inbound)
    input  logic               s_axis_tvalid,
    output logic               s_axis_tready,
    input  logic [15:0]        s_axis_tdata,

    // AXI4-Stream Manager (Outbound)
    output logic               m_axis_tvalid,
    input  logic               m_axis_tready,
    output logic [31:0]        m_axis_tdata
);

    // =========================================================================
    // Glue Logic / Internal Connections
    // Explanation: The 'axi_interface' module internally handles the width conversion 
    // (splitting the 16-bit tdata into two 8-bit operands) and handshake adaptation. 
    // Therefore, the top-level glue logic consists purely of direct wire connections 
    // routing the synchronized valid/data signals directly into the compute core, 
    // and routing the 32-bit result back. No external FIFOs were required.
    // =========================================================================
    logic               core_valid_in;
    logic signed [7:0]  core_a_in;
    logic signed [7:0]  core_b_in;
    logic               core_valid_out;
    logic signed [31:0] core_result;

    // Instantiate the AXI Interface
    axi_interface intf_inst (
        .clk(clk),
        .rst(rst),
        .s_axis_tvalid(s_axis_tvalid),
        .s_axis_tready(s_axis_tready),
        .s_axis_tdata(s_axis_tdata),
        .m_axis_tvalid(m_axis_tvalid),
        .m_axis_tready(m_axis_tready),
        .m_axis_tdata(m_axis_tdata),
        .core_valid_in(core_valid_in),
        .core_a_in(core_a_in),
        .core_b_in(core_b_in),
        .core_valid_out(core_valid_out),
        .core_result(core_result)
    );

    // Instantiate the Compute Core
    compute_core core_inst (
        .clk(clk),
        .rst(rst),
        .valid_in(core_valid_in),
        .a_in(core_a_in),
        .b_in(core_b_in),
        .valid_out(core_valid_out),
        .result(core_result)
    );

endmodule

project/m4/tb/tb_top.sv
`timescale 1ns/1ps

module tb_top;
    // Clock and Reset
    logic clk;
    logic rst;

    // AXI4-Stream Subordinate (Inbound to Top)
    logic        s_axis_tvalid;
    logic        s_axis_tready;
    logic [15:0] s_axis_tdata;

    // AXI4-Stream Manager (Outbound from Top)
    logic        m_axis_tvalid;
    logic        m_axis_tready;
    logic [31:0] m_axis_tdata;

    int output_count;

    // Instantiate the Integrated Top Module (DUT)
    top dut (
        .clk(clk),
        .rst(rst),
        .s_axis_tvalid(s_axis_tvalid),
        .s_axis_tready(s_axis_tready),
        .s_axis_tdata(s_axis_tdata),
        .m_axis_tvalid(m_axis_tvalid),
        .m_axis_tready(m_axis_tready),
        .m_axis_tdata(m_axis_tdata)
    );

    // Clock generation (10ns period)
    initial begin
        clk = 0;
        forever #5 clk = ~clk;
    end

    // Input Driver Thread (Pumps 100 pixels in)
    initial begin
        $dumpfile("m4_cosim.vcd");
        $dumpvars(0, tb_top);

        // Initialize signals
        rst = 1;
        s_axis_tvalid = 0;
        s_axis_tdata = 0;
        m_axis_tready = 0;
        output_count = 0;

        // Release reset
        @(negedge clk);
        @(negedge clk);
        rst = 0;
        m_axis_tready = 1; // Downstream is always ready to receive

        // Pump in 100 sequential pixels (simulating ~3.5 rows of an image)
        for (int i = 0; i < 100; i++) begin
            @(negedge clk);
            s_axis_tvalid = 1;
            // Pad the top 8 bits with 0, put the pixel data in the bottom 8 bits
            s_axis_tdata = {8'd0, i[7:0]}; 
            
            // Wait for handshake
            wait(s_axis_tready == 1'b1);
        end

        // Stop sending data
        @(negedge clk);
        s_axis_tvalid = 0;

        // Wait a few more clock cycles for the final pixels to drain out of the pipeline
        #500;
        
        $display("---------------------------------");
        $display("SIMULATION COMPLETE");
        $display("Total valid outputs generated: %0d", output_count);
        $display("---------------------------------");
        $finish;
    end

    // Output Monitor Thread (Watches for results)
    always @(posedge clk) begin
        if (m_axis_tvalid && m_axis_tready && !rst) begin
            $display("Time: %0t | Output #%0d | Result: %0d", $time, output_count, $signed(m_axis_tdata));
            output_count++;
        end
    end

endmodule

project/m4/sim/m4_cosim.vcd
$date
	Mon Jun  8 02:16:34 2026
$end
$version
	Icarus Verilog
$end
$timescale
	1ps
$end
$scope module tb_top $end
$var wire 1 ! s_axis_tready $end
$var wire 1 " m_axis_tvalid $end
$var wire 32 # m_axis_tdata [31:0] $end
$var reg 1 $ clk $end
$var reg 1 % m_axis_tready $end
$var reg 1 & rst $end
$var reg 16 ' s_axis_tdata [15:0] $end
$var reg 1 ( s_axis_tvalid $end
$var integer 32 ) output_count [31:0] $end
$scope module dut $end
$var wire 1 $ clk $end
$var wire 1 % m_axis_tready $end
$var wire 1 & rst $end
$var wire 16 * s_axis_tdata [15:0] $end
$var wire 1 ( s_axis_tvalid $end
$var wire 1 ! s_axis_tready $end
$var wire 1 " m_axis_tvalid $end
$var wire 32 + m_axis_tdata [31:0] $end
$var wire 1 , core_valid_out $end
$var wire 1 - core_valid_in $end
$var wire 32 . core_result [31:0] $end
$var wire 8 / core_b_in [7:0] $end
$var wire 8 0 core_a_in [7:0] $end
$scope module core_inst $end
$var wire 1 $ clk $end
$var wire 32 1 result [31:0] $end
$var wire 1 & rst $end
$var wire 1 , valid_out $end
$var wire 1 2 window_valid $end
$var wire 1 - valid_in $end
$var wire 8 3 b_in [7:0] $end
$var wire 8 4 a_in [7:0] $end
$var parameter 32 5 IMG_WIDTH $end
$var parameter 8 6 W00 $end
$var parameter 8 7 W01 $end
$var parameter 8 8 W02 $end
$var parameter 8 9 W10 $end
$var parameter 8 : W11 $end
$var parameter 8 ; W12 $end
$var parameter 8 < W20 $end
$var parameter 8 = W21 $end
$var parameter 8 > W22 $end
$var reg 5 ? col_cnt [4:0] $end
$var reg 5 @ row_cnt [4:0] $end
$var reg 32 A sum [31:0] $end
$var reg 1 B valid_pipe_1 $end
$var reg 1 C valid_pipe_2 $end
$scope begin $ivl_for_loop1 $end
$var integer 32 D i [31:0] $end
$upscope $end
$scope begin $ivl_for_loop2 $end
$var integer 32 E i [31:0] $end
$upscope $end
$upscope $end
$scope module intf_inst $end
$var wire 1 $ clk $end
$var wire 32 F core_result [31:0] $end
$var wire 1 - core_valid_in $end
$var wire 1 , core_valid_out $end
$var wire 1 % m_axis_tready $end
$var wire 1 & rst $end
$var wire 16 G s_axis_tdata [15:0] $end
$var wire 1 ! s_axis_tready $end
$var wire 1 ( s_axis_tvalid $end
$var wire 8 H core_b_in [7:0] $end
$var wire 8 I core_a_in [7:0] $end
$var reg 32 J m_axis_tdata [31:0] $end
$var reg 1 " m_axis_tvalid $end
$upscope $end
$upscope $end
$scope begin $ivl_for_loop0 $end
$var integer 32 K i [31:0] $end
$upscope $end
$upscope $end
$enddefinitions $end
$comment Show the parameter values. $end
$dumpall
b11111111 >
b11111110 =
b11111111 <
b0 ;
b0 :
b0 9
b1 8
b10 7
b1 6
b11100 5
$end
#0
$dumpvars
b0 K
bx J
b0 I
b0 H
b0 G
bx F
b0 E
b0 D
xC
xB
bx A
bx @
bx ?
b0 4
b0 3
x2
bx 1
b0 0
b0 /
bx .
0-
x,
bx +
b0 *
b0 )
0(
b0 '
1&
0%
0$
bx #
x"
x!
$end
#5000
1!
02
b0 #
b0 +
b0 J
0"
b0 @
b0 ?
0,
0C
0B
b0 .
b0 1
b0 F
b0 A
b1001 E
1$
#10000
0$
#15000
b1001 E
1$
#20000
1%
0&
0$
#25000
1$
#30000
1-
b1 K
1(
0$
#35000
b1 ?
b0 D
1$
#40000
b1 0
b1 4
b1 I
b10 K
b1 '
b1 *
b1 G
0$
#45000
b10 ?
b0 D
1$
#50000
b10 0
b10 4
b10 I
b11 K
b10 '
b10 *
b10 G
0$
#55000
b11 ?
b0 D
1$
#60000
b11 0
b11 4
b11 I
b100 K
b11 '
b11 *
b11 G
0$
#65000
b100 ?
b0 D
1$
#70000
b100 0
b100 4
b100 I
b101 K
b100 '
b100 *
b100 G
0$
#75000
b101 ?
b0 D
1$
#80000
b101 0
b101 4
b101 I
b110 K
b101 '
b101 *
b101 G
0$
#85000
b110 ?
b0 D
1$
#90000
b110 0
b110 4
b110 I
b111 K
b110 '
b110 *
b110 G
0$
#95000
b111 ?
b0 D
1$
#100000
b111 0
b111 4
b111 I
b1000 K
b111 '
b111 *
b111 G
0$
#105000
b1000 ?
b0 D
1$
#110000
b1000 0
b1000 4
b1000 I
b1001 K
b1000 '
b1000 *
b1000 G
0$
#115000
b1001 ?
b0 D
1$
#120000
b1001 0
b1001 4
b1001 I
b1010 K
b1001 '
b1001 *
b1001 G
0$
#125000
b1010 ?
b0 D
1$
#130000
b1010 0
b1010 4
b1010 I
b1011 K
b1010 '
b1010 *
b1010 G
0$
#135000
b1011 ?
b0 D
1$
#140000
b1011 0
b1011 4
b1011 I
b1100 K
b1011 '
b1011 *
b1011 G
0$
#145000
b1100 ?
b0 D
1$
#150000
b1100 0
b1100 4
b1100 I
b1101 K
b1100 '
b1100 *
b1100 G
0$
#155000
b1101 ?
b0 D
1$
#160000
b1101 0
b1101 4
b1101 I
b1110 K
b1101 '
b1101 *
b1101 G
0$
#165000
b1110 ?
b0 D
1$
#170000
b1110 0
b1110 4
b1110 I
b1111 K
b1110 '
b1110 *
b1110 G
0$
#175000
b1111 ?
b0 D
1$
#180000
b1111 0
b1111 4
b1111 I
b10000 K
b1111 '
b1111 *
b1111 G
0$
#185000
b10000 ?
b0 D
1$
#190000
b10000 0
b10000 4
b10000 I
b10001 K
b10000 '
b10000 *
b10000 G
0$
#195000
b10001 ?
b0 D
1$
#200000
b10001 0
b10001 4
b10001 I
b10010 K
b10001 '
b10001 *
b10001 G
0$
#205000
b10010 ?
b0 D
1$
#210000
b10010 0
b10010 4
b10010 I
b10011 K
b10010 '
b10010 *
b10010 G
0$
#215000
b10011 ?
b0 D
1$
#220000
b10011 0
b10011 4
b10011 I
b10100 K
b10011 '
b10011 *
b10011 G
0$
#225000
b10100 ?
b0 D
1$
#230000
b10100 0
b10100 4
b10100 I
b10101 K
b10100 '
b10100 *
b10100 G
0$
#235000
b10101 ?
b0 D
1$
#240000
b10101 0
b10101 4
b10101 I
b10110 K
b10101 '
b10101 *
b10101 G
0$
#245000
b10110 ?
b0 D
1$
#250000
b10110 0
b10110 4
b10110 I
b10111 K
b10110 '
b10110 *
b10110 G
0$
#255000
b10111 ?
b0 D
1$
#260000
b10111 0
b10111 4
b10111 I
b11000 K
b10111 '
b10111 *
b10111 G
0$
#265000
b11000 ?
b0 D
1$
#270000
b11000 0
b11000 4
b11000 I
b11001 K
b11000 '
b11000 *
b11000 G
0$
#275000
b11001 ?
b0 D
1$
#280000
b11001 0
b11001 4
b11001 I
b11010 K
b11001 '
b11001 *
b11001 G
0$
#285000
b11010 ?
b0 D
1$
#290000
b11010 0
b11010 4
b11010 I
b11011 K
b11010 '
b11010 *
b11010 G
0$
#295000
b11011 ?
b0 D
1$
#300000
b11011 0
b11011 4
b11011 I
b11100 K
b11011 '
b11011 *
b11011 G
0$
#305000
b1 @
b0 ?
b0 D
1$
#310000
b11100 0
b11100 4
b11100 I
b11101 K
b11100 '
b11100 *
b11100 G
0$
#315000
b1 ?
b0 D
1$
#320000
b11101 0
b11101 4
b11101 I
b11110 K
b11101 '
b11101 *
b11101 G
0$
#325000
b10 ?
b0 D
1$
#330000
b11110 0
b11110 4
b11110 I
b11111 K
b11110 '
b11110 *
b11110 G
0$
#335000
b11 ?
b0 D
1$
#340000
b11111 0
b11111 4
b11111 I
b100000 K
b11111 '
b11111 *
b11111 G
0$
#345000
b100 ?
b0 D
1$
#350000
b100000 0
b100000 4
b100000 I
b100001 K
b100000 '
b100000 *
b100000 G
0$
#355000
b101 ?
b0 D
1$
#360000
b100001 0
b100001 4
b100001 I
b100010 K
b100001 '
b100001 *
b100001 G
0$
#365000
b110 ?
b0 D
1$
#370000
b100010 0
b100010 4
b100010 I
b100011 K
b100010 '
b100010 *
b100010 G
0$
#375000
b111 ?
b0 D
1$
#380000
b100011 0
b100011 4
b100011 I
b100100 K
b100011 '
b100011 *
b100011 G
0$
#385000
b1000 ?
b0 D
1$
#390000
b100100 0
b100100 4
b100100 I
b100101 K
b100100 '
b100100 *
b100100 G
0$
#395000
b1001 ?
b0 D
1$
#400000
b100101 0
b100101 4
b100101 I
b100110 K
b100101 '
b100101 *
b100101 G
0$
#405000
b1010 ?
b0 D
1$
#410000
b100110 0
b100110 4
b100110 I
b100111 K
b100110 '
b100110 *
b100110 G
0$
#415000
b1011 ?
b0 D
1$
#420000
b100111 0
b100111 4
b100111 I
b101000 K
b100111 '
b100111 *
b100111 G
0$
#425000
b1100 ?
b0 D
1$
#430000
b101000 0
b101000 4
b101000 I
b101001 K
b101000 '
b101000 *
b101000 G
0$
#435000
b1101 ?
b0 D
1$
#440000
b101001 0
b101001 4
b101001 I
b101010 K
b101001 '
b101001 *
b101001 G
0$
#445000
b1110 ?
b0 D
1$
#450000
b101010 0
b101010 4
b101010 I
b101011 K
b101010 '
b101010 *
b101010 G
0$
#455000
b1111 ?
b0 D
1$
#460000
b101011 0
b101011 4
b101011 I
b101100 K
b101011 '
b101011 *
b101011 G
0$
#465000
b10000 ?
b0 D
1$
#470000
b101100 0
b101100 4
b101100 I
b101101 K
b101100 '
b101100 *
b101100 G
0$
#475000
b10001 ?
b0 D
1$
#480000
b101101 0
b101101 4
b101101 I
b101110 K
b101101 '
b101101 *
b101101 G
0$
#485000
b10010 ?
b0 D
1$
#490000
b101110 0
b101110 4
b101110 I
b101111 K
b101110 '
b101110 *
b101110 G
0$
#495000
b10011 ?
b0 D
1$
#500000
b101111 0
b101111 4
b101111 I
b110000 K
b101111 '
b101111 *
b101111 G
0$
#505000
b10100 ?
b0 D
1$
#510000
b110000 0
b110000 4
b110000 I
b110001 K
b110000 '
b110000 *
b110000 G
0$
#515000
b10101 ?
b0 D
1$
#520000
b110001 0
b110001 4
b110001 I
b110010 K
b110001 '
b110001 *
b110001 G
0$
#525000
b10110 ?
b0 D
1$
#530000
b110010 0
b110010 4
b110010 I
b110011 K
b110010 '
b110010 *
b110010 G
0$
#535000
b10111 ?
b0 D
1$
#540000
b110011 0
b110011 4
b110011 I
b110100 K
b110011 '
b110011 *
b110011 G
0$
#545000
b11000 ?
b0 D
1$
#550000
b110100 0
b110100 4
b110100 I
b110101 K
b110100 '
b110100 *
b110100 G
0$
#555000
b11001 ?
b0 D
1$
#560000
b110101 0
b110101 4
b110101 I
b110110 K
b110101 '
b110101 *
b110101 G
0$
#565000
b11010 ?
b0 D
1$
#570000
b110110 0
b110110 4
b110110 I
b110111 K
b110110 '
b110110 *
b110110 G
0$
#575000
b11011 ?
b0 D
1$
#580000
b110111 0
b110111 4
b110111 I
b111000 K
b110111 '
b110111 *
b110111 G
0$
#585000
b10 @
b0 ?
b0 D
1$
#590000
b111000 0
b111000 4
b111000 I
b111001 K
b111000 '
b111000 *
b111000 G
0$
#595000
b1 ?
b0 D
1$
#600000
b111001 0
b111001 4
b111001 I
b111010 K
b111001 '
b111001 *
b111001 G
0$
#605000
12
b10 ?
b0 D
1$
#610000
b111010 0
b111010 4
b111010 I
b111011 K
b111010 '
b111010 *
b111010 G
0$
#615000
b11 ?
1B
b0 D
1$
#620000
b111011 0
b111011 4
b111011 I
b111100 K
b111011 '
b111011 *
b111011 G
0$
#625000
b100 ?
1,
1C
bx .
bx 1
bx F
bx A
b0 D
1$
#630000
b111100 0
b111100 4
b111100 I
b111101 K
b111100 '
b111100 *
b111100 G
0$
#635000
b101 ?
b11111111111111111111111100100000 .
b11111111111111111111111100100000 1
b11111111111111111111111100100000 F
b11111111111111111111111100100000 A
bx #
bx +
bx J
1"
b0 D
1$
#640000
b111101 0
b111101 4
b111101 I
b111110 K
b111101 '
b111101 *
b111101 G
0$
#645000
b110 ?
b11111111111111111111111100100000 #
b11111111111111111111111100100000 +
b11111111111111111111111100100000 J
b0 D
b1 )
1$
#650000
b111110 0
b111110 4
b111110 I
b111111 K
b111110 '
b111110 *
b111110 G
0$
#655000
b111 ?
b0 D
b10 )
1$
#660000
b111111 0
b111111 4
b111111 I
b1000000 K
b111111 '
b111111 *
b111111 G
0$
#665000
b1000 ?
b0 D
b11 )
1$
#670000
b1000000 0
b1000000 4
b1000000 I
b1000001 K
b1000000 '
b1000000 *
b1000000 G
0$
#675000
b1001 ?
b0 D
b100 )
1$
#680000
b1000001 0
b1000001 4
b1000001 I
b1000010 K
b1000001 '
b1000001 *
b1000001 G
0$
#685000
b1010 ?
b0 D
b101 )
1$
#690000
b1000010 0
b1000010 4
b1000010 I
b1000011 K
b1000010 '
b1000010 *
b1000010 G
0$
#695000
b1011 ?
b0 D
b110 )
1$
#700000
b1000011 0
b1000011 4
b1000011 I
b1000100 K
b1000011 '
b1000011 *
b1000011 G
0$
#705000
b1100 ?
b0 D
b111 )
1$
#710000
b1000100 0
b1000100 4
b1000100 I
b1000101 K
b1000100 '
b1000100 *
b1000100 G
0$
#715000
b1101 ?
b0 D
b1000 )
1$
#720000
b1000101 0
b1000101 4
b1000101 I
b1000110 K
b1000101 '
b1000101 *
b1000101 G
0$
#725000
b1110 ?
b0 D
b1001 )
1$
#730000
b1000110 0
b1000110 4
b1000110 I
b1000111 K
b1000110 '
b1000110 *
b1000110 G
0$
#735000
b1111 ?
b0 D
b1010 )
1$
#740000
b1000111 0
b1000111 4
b1000111 I
b1001000 K
b1000111 '
b1000111 *
b1000111 G
0$
#745000
b10000 ?
b0 D
b1011 )
1$
#750000
b1001000 0
b1001000 4
b1001000 I
b1001001 K
b1001000 '
b1001000 *
b1001000 G
0$
#755000
b10001 ?
b0 D
b1100 )
1$
#760000
b1001001 0
b1001001 4
b1001001 I
b1001010 K
b1001001 '
b1001001 *
b1001001 G
0$
#765000
b10010 ?
b0 D
b1101 )
1$
#770000
b1001010 0
b1001010 4
b1001010 I
b1001011 K
b1001010 '
b1001010 *
b1001010 G
0$
#775000
b10011 ?
b0 D
b1110 )
1$
#780000
b1001011 0
b1001011 4
b1001011 I
b1001100 K
b1001011 '
b1001011 *
b1001011 G
0$
#785000
b10100 ?
b0 D
b1111 )
1$
#790000
b1001100 0
b1001100 4
b1001100 I
b1001101 K
b1001100 '
b1001100 *
b1001100 G
0$
#795000
b10101 ?
b0 D
b10000 )
1$
#800000
b1001101 0
b1001101 4
b1001101 I
b1001110 K
b1001101 '
b1001101 *
b1001101 G
0$
#805000
b10110 ?
b0 D
b10001 )
1$
#810000
b1001110 0
b1001110 4
b1001110 I
b1001111 K
b1001110 '
b1001110 *
b1001110 G
0$
#815000
b10111 ?
b0 D
b10010 )
1$
#820000
b1001111 0
b1001111 4
b1001111 I
b1010000 K
b1001111 '
b1001111 *
b1001111 G
0$
#825000
b11000 ?
b0 D
b10011 )
1$
#830000
b1010000 0
b1010000 4
b1010000 I
b1010001 K
b1010000 '
b1010000 *
b1010000 G
0$
#835000
b11001 ?
b0 D
b10100 )
1$
#840000
b1010001 0
b1010001 4
b1010001 I
b1010010 K
b1010001 '
b1010001 *
b1010001 G
0$
#845000
b11010 ?
b0 D
b10101 )
1$
#850000
b1010010 0
b1010010 4
b1010010 I
b1010011 K
b1010010 '
b1010010 *
b1010010 G
0$
#855000
b11011 ?
b0 D
b10110 )
1$
#860000
b1010011 0
b1010011 4
b1010011 I
b1010100 K
b1010011 '
b1010011 *
b1010011 G
0$
#865000
02
b11 @
b0 ?
b0 D
b10111 )
1$
#870000
b1010100 0
b1010100 4
b1010100 I
b1010101 K
b1010100 '
b1010100 *
b1010100 G
0$
#875000
b1 ?
0B
b0 D
b11000 )
1$
#880000
b1010101 0
b1010101 4
b1010101 I
b1010110 K
b1010101 '
b1010101 *
b1010101 G
0$
#885000
12
b10 ?
0,
0C
b0 D
b11001 )
1$
#890000
b1010110 0
b1010110 4
b1010110 I
b1010111 K
b1010110 '
b1010110 *
b1010110 G
0$
#895000
b11 ?
1B
0"
b0 D
b11010 )
1$
#900000
b1010111 0
b1010111 4
b1010111 I
b1011000 K
b1010111 '
b1010111 *
b1010111 G
0$
#905000
b100 ?
1,
1C
b0 D
1$
#910000
b1011000 0
b1011000 4
b1011000 I
b1011001 K
b1011000 '
b1011000 *
b1011000 G
0$
#915000
b101 ?
1"
b0 D
1$
#920000
b1011001 0
b1011001 4
b1011001 I
b1011010 K
b1011001 '
b1011001 *
b1011001 G
0$
#925000
b110 ?
b0 D
b11011 )
1$
#930000
b1011010 0
b1011010 4
b1011010 I
b1011011 K
b1011010 '
b1011010 *
b1011010 G
0$
#935000
b111 ?
b0 D
b11100 )
1$
#940000
b1011011 0
b1011011 4
b1011011 I
b1011100 K
b1011011 '
b1011011 *
b1011011 G
0$
#945000
b1000 ?
b0 D
b11101 )
1$
#950000
b1011100 0
b1011100 4
b1011100 I
b1011101 K
b1011100 '
b1011100 *
b1011100 G
0$
#955000
b1001 ?
b0 D
b11110 )
1$
#960000
b1011101 0
b1011101 4
b1011101 I
b1011110 K
b1011101 '
b1011101 *
b1011101 G
0$
#965000
b1010 ?
b0 D
b11111 )
1$
#970000
b1011110 0
b1011110 4
b1011110 I
b1011111 K
b1011110 '
b1011110 *
b1011110 G
0$
#975000
b1011 ?
b0 D
b100000 )
1$
#980000
b1011111 0
b1011111 4
b1011111 I
b1100000 K
b1011111 '
b1011111 *
b1011111 G
0$
#985000
b1100 ?
b0 D
b100001 )
1$
#990000
b1100000 0
b1100000 4
b1100000 I
b1100001 K
b1100000 '
b1100000 *
b1100000 G
0$
#995000
b1101 ?
b0 D
b100010 )
1$
#1000000
b1100001 0
b1100001 4
b1100001 I
b1100010 K
b1100001 '
b1100001 *
b1100001 G
0$
#1005000
b1110 ?
b0 D
b100011 )
1$
#1010000
b1100010 0
b1100010 4
b1100010 I
b1100011 K
b1100010 '
b1100010 *
b1100010 G
0$
#1015000
b1111 ?
b0 D
b100100 )
1$
#1020000
b1100011 0
b1100011 4
b1100011 I
b1100100 K
b1100011 '
b1100011 *
b1100011 G
0$
#1025000
b10000 ?
b0 D
b100101 )
1$
#1030000
0-
0(
0$
#1035000
0B
b100110 )
1$
#1040000
0$
#1045000
0,
0C
b100111 )
1$
#1050000
0$
#1055000
0"
b101000 )
1$
